SimPEG/__init__.py
SimPEG/data.py
SimPEG/data_misfit.py
SimPEG/directives.py
SimPEG/fields.py
SimPEG/inverse_problem.py
SimPEG/inversion.py
SimPEG/maps.py
SimPEG/models.py
SimPEG/objective_function.py
SimPEG/old_api.py
SimPEG/optimization.py
SimPEG/props.py
SimPEG/simulation.py
SimPEG/survey.py
SimPEG/dask/__init__.py
SimPEG/dask/simulation.py
SimPEG/dask/utils.py
SimPEG/dask/electromagnetics/__init__.py
SimPEG/dask/electromagnetics/static/__init__.py
SimPEG/dask/electromagnetics/static/induced_polarization/__init__.py
SimPEG/dask/electromagnetics/static/induced_polarization/simulation.py
SimPEG/dask/electromagnetics/static/resistivity/__init__.py
SimPEG/dask/electromagnetics/static/resistivity/simulation.py
SimPEG/dask/potential_fields/__init__.py
SimPEG/dask/potential_fields/base.py
SimPEG/dask/potential_fields/gravity/__init__.py
SimPEG/dask/potential_fields/gravity/simulation.py
SimPEG/dask/potential_fields/magnetics/__init__.py
SimPEG/dask/potential_fields/magnetics/simulation.py
SimPEG/electromagnetics/__init__.py
SimPEG/electromagnetics/base.py
SimPEG/electromagnetics/analytics/DC.py
SimPEG/electromagnetics/analytics/FDEM.py
SimPEG/electromagnetics/analytics/FDEMDipolarfields.py
SimPEG/electromagnetics/analytics/FDEMcasing.py
SimPEG/electromagnetics/analytics/NSEM.py
SimPEG/electromagnetics/analytics/TDEM.py
SimPEG/electromagnetics/analytics/__init__.py
SimPEG/electromagnetics/frequency_domain/__init__.py
SimPEG/electromagnetics/frequency_domain/fields.py
SimPEG/electromagnetics/frequency_domain/receivers.py
SimPEG/electromagnetics/frequency_domain/simulation.py
SimPEG/electromagnetics/frequency_domain/sources.py
SimPEG/electromagnetics/frequency_domain/survey.py
SimPEG/electromagnetics/natural_source/__init__.py
SimPEG/electromagnetics/natural_source/fields.py
SimPEG/electromagnetics/natural_source/receivers.py
SimPEG/electromagnetics/natural_source/simulation.py
SimPEG/electromagnetics/natural_source/sources.py
SimPEG-0.14.2.dist-info/AUTHORS.rst
SimPEG-0.14.2.dist-info/LICENSE
SimPEG-0.14.2.dist-info/METADATA
SimPEG-0.14.2.dist-info/WHEEL
SimPEG-0.14.2.dist-info/top_level.txt
SimPEG-0.14.2.dist-info/RECORD
