Metadata-Version: 2.1
Name: SimPEG
Version: 0.14.2
Summary: SimPEG: Simulation and Parameter Estimation in Geophysics
Home-page: http://simpeg.xyz/
Author: Rowan Cockett
Author-email: rowanc1@gmail.com
License: MIT
Download-URL: http://github.com/simpeg/simpeg
Keywords: geophysics inverse problem
Platform: Windows
Platform: Linux
Platform: Solaris
Platform: Mac OS-X
Platform: Unix
Classifier: Development Status :: 4 - Beta
Classifier: Intended Audience :: Developers
Classifier: Intended Audience :: Science/Research
Classifier: License :: OSI Approved :: MIT License
Classifier: Programming Language :: Python
Classifier: Topic :: Scientific/Engineering
Classifier: Topic :: Scientific/Engineering :: Mathematics
Classifier: Topic :: Scientific/Engineering :: Physics
Classifier: Operating System :: Microsoft :: Windows
Classifier: Operating System :: POSIX
Classifier: Operating System :: Unix
Classifier: Operating System :: MacOS
Classifier: Natural Language :: English
Requires-Dist: numpy (>=1.7)
Requires-Dist: scipy (>=0.13)
Requires-Dist: pymatsolver (>=0.1.1)
Requires-Dist: matplotlib
Requires-Dist: properties (>=0.5.2)
Requires-Dist: vectormath (>=0.2.0)
Requires-Dist: discretize (>=0.4.0)
Requires-Dist: geoana (>=0.0.4)
Requires-Dist: empymod
Requires-Dist: pandas
